duqo/__init__.py
duqo/doe/__init__.py
duqo/doe/hyperspace_division.py
duqo/doe/lhs.py
duqo/lolhr/__init__.py
duqo/lolhr/rrdo_lolhr.py
duqo/optimization/__init__.py
duqo/optimization/predict.py
duqo/optimization/rrdo.py
duqo/optimization/space.py
duqo/proba/__init__.py
duqo/proba/_integrator_base.py
duqo/proba/ds.py
duqo/proba/mc.py
duqo/stoch/__init__.py
duqo/stoch/copula.py
duqo/stoch/get_margs.py
duqo/stoch/model.py
duqo/uml/__init__.py
duqo/uml/clustering.py
duqo-0.0a1.dist-info/LICENSE
duqo-0.0a1.dist-info/METADATA
duqo-0.0a1.dist-info/WHEEL
duqo-0.0a1.dist-info/top_level.txt
duqo-0.0a1.dist-info/RECORD
