Metadata-Version: 2.1
Name: duqo
Version: 0.0a1
Summary: A framework for (D)esign (U)ncertainty (Q)uantification and (O)ptimization
Home-page: https://github.com/canbooo/duqo
Author: Can Bogoclu
Author-email: can.bogoclu@gmail.com
License: BSD 3-Clause License
Project-URL: Bug Tracker, https://github.com/canbooo/duqo/issues
Platform: any
Classifier: Intended Audience :: Science/Research
Classifier: Intended Audience :: Developers
Classifier: Programming Language :: Python
Classifier: Topic :: Software Development
Classifier: Topic :: Scientific/Engineering
Classifier: Operating System :: Microsoft :: Windows
Classifier: Operating System :: POSIX
Classifier: Operating System :: Unix
Classifier: Operating System :: MacOS
Classifier: Programming Language :: Python :: 3
Classifier: Programming Language :: Python :: 3.7
Classifier: Programming Language :: Python :: 3.8
Classifier: Programming Language :: Python :: 3.9
Classifier: License :: OSI Approved :: BSD License
Requires-Python: >=3.7
Requires-Dist: numpy (>=1.18.1)
Requires-Dist: scipy (>=1.4.1)
Requires-Dist: scikit-learn (>=0.22.1)
Requires-Dist: pandas (>=1.3.1)
Requires-Dist: matplotlib (>=3.4.2)
